[
  {
    "ticker": "SPY",
    "name": "S&P 500",
    "theme": "broad_market",
    "price": 733.24,
    "sma_50": 732.97,
    "sma_200": 689.72,
    "rsi_14": 39.5,
    "price_vs_sma50_pct": 0,
    "price_vs_sma200_pct": 6.3,
    "drawdown_from_high": -3.6,
    "date": "2026-06-25",
    "dca_signal": "steady"
  },
  {
    "ticker": "QQQ",
    "name": "Nasdaq 100",
    "theme": "tech_ai",
    "price": 710.62,
    "sma_50": 699.66,
    "sma_200": 630.84,
    "rsi_14": 41.3,
    "price_vs_sma50_pct": 1.6,
    "price_vs_sma200_pct": 12.6,
    "drawdown_from_high": -5.1,
    "date": "2026-06-25",
    "dca_signal": "steady"
  },
  {
    "ticker": "TLT",
    "name": "20+ Year Treasury",
    "theme": "treasury_bonds",
    "price": 87.38,
    "sma_50": 85.64,
    "sma_200": 87.91,
    "rsi_14": 66.8,
    "price_vs_sma50_pct": 2,
    "price_vs_sma200_pct": -0.6,
    "drawdown_from_high": -5.2,
    "date": "2026-06-25",
    "dca_signal": "steady"
  },
  {
    "ticker": "ICLN",
    "name": "Global Clean Energy",
    "theme": "clean_energy",
    "price": 20.48,
    "sma_50": 21.17,
    "sma_200": 18.19,
    "rsi_14": 32,
    "price_vs_sma50_pct": -3.3,
    "price_vs_sma200_pct": 12.6,
    "drawdown_from_high": -13.9,
    "date": "2026-06-25",
    "dca_signal": "accelerate"
  },
  {
    "ticker": "VNQ",
    "name": "Vanguard Real Estate",
    "theme": "real_estate",
    "price": 97.01,
    "sma_50": 96.07,
    "sma_200": 92.2,
    "rsi_14": 59.7,
    "price_vs_sma50_pct": 1,
    "price_vs_sma200_pct": 5.2,
    "drawdown_from_high": -2.2,
    "date": "2026-06-25",
    "dca_signal": "steady"
  },
  {
    "ticker": "XLV",
    "name": "Health Care Select",
    "theme": "healthcare",
    "price": 153.35,
    "sma_50": 148.13,
    "sma_200": 149.57,
    "rsi_14": 64.9,
    "price_vs_sma50_pct": 3.5,
    "price_vs_sma200_pct": 2.5,
    "drawdown_from_high": -4.5,
    "date": "2026-06-25",
    "dca_signal": "steady"
  },
  {
    "ticker": "XLF",
    "name": "Financial Select",
    "theme": "financials",
    "price": 53.72,
    "sma_50": 52.09,
    "sma_200": 52.55,
    "rsi_14": 74.4,
    "price_vs_sma50_pct": 3.1,
    "price_vs_sma200_pct": 2.2,
    "drawdown_from_high": -5,
    "date": "2026-06-25",
    "dca_signal": "steady"
  },
  {
    "ticker": "XLE",
    "name": "Energy Select",
    "theme": "energy",
    "price": 53.57,
    "sma_50": 57.26,
    "sma_200": 51.06,
    "rsi_14": 25.5,
    "price_vs_sma50_pct": -6.4,
    "price_vs_sma200_pct": 4.9,
    "drawdown_from_high": -15.6,
    "date": "2026-06-25",
    "dca_signal": "accelerate"
  },
  {
    "ticker": "XLY",
    "name": "Consumer Discretionary",
    "theme": "consumer",
    "price": 115.07,
    "sma_50": 117.79,
    "sma_200": 117.61,
    "rsi_14": 46,
    "price_vs_sma50_pct": -2.3,
    "price_vs_sma200_pct": -2.2,
    "drawdown_from_high": -8,
    "date": "2026-06-25",
    "dca_signal": "steady"
  },
  {
    "ticker": "ITA",
    "name": "US Aerospace & Defense",
    "theme": "defense",
    "price": 236.19,
    "sma_50": 226.84,
    "sma_200": 221.36,
    "rsi_14": 61.3,
    "price_vs_sma50_pct": 4.1,
    "price_vs_sma200_pct": 6.7,
    "drawdown_from_high": -5.8,
    "date": "2026-06-25",
    "dca_signal": "steady"
  },
  {
    "ticker": "DBC",
    "name": "Invesco DB Commodity",
    "theme": "commodities",
    "price": 26.45,
    "sma_50": 29.73,
    "sma_200": 25.52,
    "rsi_14": 7.5,
    "price_vs_sma50_pct": -11,
    "price_vs_sma200_pct": 3.7,
    "drawdown_from_high": -16.8,
    "date": "2026-06-25",
    "dca_signal": "accelerate"
  },
  {
    "ticker": "ESGV",
    "name": "Vanguard ESG US Stock",
    "theme": "esg_broad",
    "price": 129.65,
    "sma_50": 129.12,
    "sma_200": 121.52,
    "rsi_14": 40.4,
    "price_vs_sma50_pct": 0.4,
    "price_vs_sma200_pct": 6.7,
    "drawdown_from_high": -4,
    "date": "2026-06-25",
    "dca_signal": "steady"
  },
  {
    "ticker": "QCLN",
    "name": "First Trust NASDAQ Clean Edge",
    "theme": "clean_energy_us",
    "price": 60.52,
    "sma_50": 60.43,
    "sma_200": 49.72,
    "rsi_14": 36.8,
    "price_vs_sma50_pct": 0.1,
    "price_vs_sma200_pct": 21.7,
    "drawdown_from_high": -12.5,
    "date": "2026-06-25",
    "dca_signal": "accelerate"
  },
  {
    "ticker": "PHO",
    "name": "Invesco Water Resources",
    "theme": "water",
    "price": 67.91,
    "sma_50": 67.21,
    "sma_200": 70.4,
    "rsi_14": 57.7,
    "price_vs_sma50_pct": 1,
    "price_vs_sma200_pct": -3.5,
    "drawdown_from_high": -9.4,
    "date": "2026-06-25",
    "dca_signal": "accelerate"
  }
]